yjira/__init__.py
yjira/__main__.py
yjira/config.toml
yjira/viewer.py
ybt_jira-1.0.2.dist-info/LICENSE
ybt_jira-1.0.2.dist-info/METADATA
ybt_jira-1.0.2.dist-info/WHEEL
ybt_jira-1.0.2.dist-info/entry_points.txt
ybt_jira-1.0.2.dist-info/top_level.txt
ybt_jira-1.0.2.dist-info/RECORD
