Metadata-Version: 2.1
Name: ybt-jira
Version: 1.0.2
Summary: TODO: add description
Author-email: y24 ved <y24.ved@gmail.com>
License: MIT License        
Project-URL: Homepage, https://github.com/y24ved/ybt-jira
Keywords: jira
Classifier: License :: OSI Approved :: MIT License
Classifier: Programming Language :: Python
Classifier: Programming Language :: Python :: 3
Classifier: Operating System :: POSIX :: Linux
Requires-Python: >=3.6
License-File: LICENSE
Requires-Dist: tomli
Requires-Dist: jira
Requires-Dist: rich
Requires-Dist: filemagic ; python_version < "3.7"
Provides-Extra: dev
Requires-Dist: pytest ; extra == 'dev'
Requires-Dist: bumpver ; extra == 'dev'
Requires-Dist: autopep8 ; extra == 'dev'
Requires-Dist: pip-tools ; extra == 'dev'
